toppyt/__init__.py
toppyt/applications.py
toppyt/background.py
toppyt/bulma.py
toppyt/datasources.py
toppyt/interactions.py
toppyt/patterns.py
toppyt/tasks.py
toppyt/toppyt.js
toppyt-0.7.3.dist-info/LICENSE
toppyt-0.7.3.dist-info/METADATA
toppyt-0.7.3.dist-info/WHEEL
toppyt-0.7.3.dist-info/RECORD
